{
  "version": "0.3.14-fixed",
  "steps": [
    {
      "tag": "CreateDirective",
      "location": {
        "path": {
          "tag": "Field",
          "model": "Form",
          "field": "name"
        },
        "directive": "default"
      }
    },
    {
      "tag": "CreateArgument",
      "location": {
        "tag": "Directive",
        "path": {
          "tag": "Field",
          "model": "Form",
          "field": "name"
        },
        "directive": "default"
      },
      "argument": "",
      "value": "\"\""
    }
  ]
}